LICENSE
MANIFEST.in
README.md
panpun.py
setup.py
TuiTse_TsuSin.egg-info/PKG-INFO
TuiTse_TsuSin.egg-info/SOURCES.txt
TuiTse_TsuSin.egg-info/dependency_links.txt
TuiTse_TsuSin.egg-info/requires.txt
TuiTse_TsuSin.egg-info/top_level.txt
test/test_boolean.py
test/test_html.py
test/test_kiamtsa.py
test/test_pau.py
test/test_tng_tuitse.py
test/test_tuitse_tsinghap.py
test/test_widget.py
tuitse/__init__.py
tuitse/_kiamtsa.py
tuitse/_pau.py
tuitse/boolean.py
tuitse/constant.py
tuitse/html.py
tuitse/widget.py