Metadata-Version: 2.1
Name: TuiTse-TsuSin
Version: 1.3.2
Summary: 對齊資訊
Home-page: https://ithuan.tw/
Download-URL: https://github.com/i3thuan5/TuiTse-TsuSin
Author: Tshuà Bûn-lī
Author-email: ithuan@ithuan.tw
Keywords: Parser,Alignment,Taigi,Hanji,Lomaji
Classifier: Development Status :: 5 - Production/Stable
Classifier: Operating System :: Unix
Classifier: Programming Language :: Python :: 3.8
Classifier: Programming Language :: Python :: 3.9
Classifier: Topic :: Text Processing
Classifier: Topic :: Text Processing :: Linguistic
License-File: LICENSE
Requires-Dist: kau3-tian2-iong7-ji7<4.0.0,>=2.1.0
Requires-Dist: tai5-uan5_gian5-gi2_kang1-ku7<2.0.0,>=1.1.0
